amg.py
const.py
setup.cfg
setup.py
amg.egg-info/PKG-INFO
amg.egg-info/SOURCES.txt
amg.egg-info/dependency_links.txt
amg.egg-info/entry_points.txt
amg.egg-info/requires.txt
amg.egg-info/top_level.txt
amg.egg-info/zip-safe