Metadata-Version: 1.0
Name: amg
Version: 1.0.6
Summary: app manager tool
Home-page: UNKNOWN
Author: zewait
Author-email: wait@h4fan.com
License: MIT
Platform: UNKNOWN
